conntility/__init__.py
conntility/connectivity.py
conntility/multi_scale.py
conntility/plugins.py
conntility/analysis/__init__.py
conntility/analysis/analysis.py
conntility/analysis/analysis_decorators.py
conntility/analysis/clustering.py
conntility/analysis/library/__init__.py
conntility/analysis/library/diffusion_mapping.py
conntility/circuit_models/__init__.py
conntility/circuit_models/connection_matrix.py
conntility/circuit_models/input_spikes.py
conntility/circuit_models/sonata_helpers.py
conntility/circuit_models/neuron_groups/__init__.py
conntility/circuit_models/neuron_groups/defaults.py
conntility/circuit_models/neuron_groups/extra_properties.py
conntility/circuit_models/neuron_groups/from_atlas.py
conntility/circuit_models/neuron_groups/grouping_config.py
conntility/circuit_models/neuron_groups/loader.py
conntility/circuit_models/neuron_groups/make_groups.py
conntility/circuit_models/neuron_groups/sonata_extensions.py
conntility/circuit_models/neuron_groups/tessellate.py
conntility/flatmapping/__init__.py
conntility/flatmapping/_supersample_utility.py
conntility/flatmapping/flatmap_utility.py
conntility/flatmapping/supersampling.py
conntility/flatmapping/wm_recipe_utility.py
conntility/io/__init__.py
conntility/io/sparse_matrices.py
conntility/io/synapse_report.py
conntility/randomization/__init__.py
conntility/subcellular/__init__.py
conntility/subcellular/neuron_morphology_path_distance.py
connectome_utilities-0.4.11.dist-info/AUTHORS.txt
connectome_utilities-0.4.11.dist-info/LICENSE
connectome_utilities-0.4.11.dist-info/METADATA
connectome_utilities-0.4.11.dist-info/WHEEL
connectome_utilities-0.4.11.dist-info/top_level.txt
connectome_utilities-0.4.11.dist-info/RECORD
