Metadata-Version: 2.1
Name: Connectome-Utilities
Version: 0.4.11
Summary: Complex network representation and analysis layer
Author-email: Open Brain Institute <conntility.645co@simplelogin.com>
Project-URL: Homepage, https://github.com/openbraininstitute/ConnectomeUtilities
Project-URL: Bug Tracker, https://github.com/openbraininstitute/ConnectomeUtilities/issues
Classifier: Programming Language :: Python :: 3
Classifier: Operating System :: OS Independent
Classifier: Development Status :: 5 - Production/Stable
Classifier: Intended Audience :: Science/Research
Requires-Python: >=3.8
License-File: LICENSE
License-File: AUTHORS.txt
Requires-Dist: numpy >=1.20.0
Requires-Dist: h5py >=3.6.0
Requires-Dist: pandas >=2.0.0
Requires-Dist: tables >=3.6
Requires-Dist: scipy >=1.8.0
Requires-Dist: tqdm >=4.50.0
Requires-Dist: lazy >=1.4
Requires-Dist: scikit-learn
Requires-Dist: libsonata >=0.1.10
Requires-Dist: bluepysnap >=1.0.0
Requires-Dist: voxcell
